th_txmessage/__init__.py
th_txmessage/consume.py
th_txmessage/message_task.py
th_txmessage/rabbitmq_utils.py
th_txmessage/sender.py
th_txmessage/sender_test.py
th_txmessage/test.py
th_txmessage/tx_ms_utils.py
th_txmessage-4.1.7.dist-info/METADATA
th_txmessage-4.1.7.dist-info/WHEEL
th_txmessage-4.1.7.dist-info/top_level.txt
th_txmessage-4.1.7.dist-info/RECORD
