Metadata-Version: 2.1
Name: th-txmessage
Version: 4.1.7
Summary: 听海内部爬虫核心类库
Home-page: UNKNOWN
Author: wzr
Author-email: 510540795@qq.com
License: MIT Licence
Platform: any
Requires-Dist: apscheduler
Requires-Dist: qcloud-cmq-sdk-py3
Requires-Dist: requests
Requires-Dist: retry
